[
    {
        "id": 1,
        "nombre": "Don Julio",
        "fotoUrl": "https://media.diageocms.com/media/e2ldx0cd/spirits-beer-and-drinks_our-brands_tequila_don-julio-generic-promo.png",
        "productos": [
            {
                "id": 1,
                "nombre": "DON JULIO 70",
                "precio": 749,
                "cantidad": 1000,
                "fotoUrl": "assets/img/julio70.png",
                "descripcion": "El primer tequila añejo cristalino del mundo. Combina la suavidad de un tequila añejo con la frescura de un blanco. Sus notas de vainilla, miel y roble hacen de este tequila una experiencia única y elegante.",
                "disponible": true
            },
            {
                "id": 2,
                "nombre": "DON JULIO REPOSADO",
                "precio": 649,
                "cantidad": 1000,
                "fotoUrl": "assets/img/julioReposado.png",
                "descripcion": "Un tequila de cuerpo medio con notas suaves y equilibradas de frutas secas, caramelo y un toque de madera. Reposado durante ocho meses en barricas de roble americano.",
                "disponible": true
            },
            {
                "id": 3,
                "nombre": "DON JULIO BLANCO",
                "precio": 549,
                "cantidad": 1000,
                "fotoUrl": "assets/img/julioBlanco.png",
                "descripcion": "La esencia pura del agave azul. Este tequila cristalino y fresco destaca por sus notas cítricas, de pimienta y hierbas.",
                "disponible": true
            }
        ]
    },
    {
        "id": 2,
        "nombre": "Tradicional",
        "fotoUrl": "https://vinosamerica.com/cdn/shop/products/7501035012219_4_720x.jpg?v=1685321515",
        "productos": [
            {
                "id": 1,
                "nombre": "TRAD CRISTALINO",
                "precio": 449,
                "cantidad": 1000,
                "fotoUrl": "https://vinotecamx.vtexassets.com/arquivos/ids/1346294/T28533-Vinoteca-Tequila-Tradicional-Cristalino-750Ml-003.jpg?v=638646735697130000",
                "descripcion": "Un tequila añejo cristalino que destaca por su suavidad y pureza. Conserva los sabores ricos de la madera y el agave maduro, con un acabado dulce y ligero.",
                "disponible": true
            },
            {
                "id": 2,
                "nombre": "TRAD PLATA",
                "precio": 369,
                "cantidad": 1000,
                "fotoUrl": "https://www.lanaval.com.mx/93471-large_default/tequila-jose-cuervo-tradicional-plata-695ml.jpg",
                "descripcion": "Un tequila fresco y auténtico, elaborado con agave azul 100% mexicano. Suave en el paladar, con notas cítricas y herbales, es perfecto para margaritas y otros cócteles, o para disfrutar puro con un toque de sal y limón",
                "disponible": true
            },
            {
                "id": 3,
                "nombre": "TRAD REPOSADO",
                "precio": 369,
                "cantidad": 1000,
                "fotoUrl": "https://encrypted-tbn0.gstatic.com/images?q=tbn:ANd9GcTszRJCvjz_ch8WNfZZH_VQ9r7dquvBRFV5jA&s",
                "descripcion": "Este tequila reposado ofrece el equilibrio perfecto entre suavidad y carácter. Envejecido en barricas de roble, tiene notas cálidas de vainilla, caramelo y un toque de especias.",
                "disponible": true
            }
        ]
    },
    {
        "id": 3,
        "nombre": "Centenario",
        "fotoUrl": "https://http2.mlstatic.com/D_NQ_NP_636886-MLM47718256233_092021-O.webp",
        "productos": [
            {
                "id": 1,
                "nombre": "CENTENARIO PLATA",
                "precio": 330,
                "cantidad": 1000,
                "fotoUrl": "https://varrica.mx/wp-content/uploads/2024/08/CENTENARIO1LT.jpeg",
                "descripcion": "Un tequila suave y brillante, elaborado con agave azul 100%. Destaca por sus notas frescas de agave y cítricos, lo que lo convierte en una elección ideal para cócteles o para disfrutar puro con hielo.",
                "disponible": true
            },
            {
                "id": 2,
                "nombre": "CENTENARIO REPOSADO",
                "precio": 330,
                "cantidad": 1000,
                "fotoUrl": "https://i5.walmartimages.com.mx/mg/gm/1p/images/product-images/img_large/00750104881001l.jpg?odnHeight=612&odnWidth=612&odnBg=FFFFFF",
                "descripcion": "Tequila de sabor equilibrado, reposado en barricas de roble para obtener notas cálidas de caramelo, vainilla y especias. Perfecto para disfrutar solo o como base de bebidas sofisticadas.",
                "disponible": true
            }
        ]
    },
    {
        "id": 4,
        "nombre": "Buchanans",
        "fotoUrl": "https://encrypted-tbn0.gstatic.com/images?q=tbn:ANd9GcQsM6U8HG2CY7EBU9Q67BYKEpkBLptYot9vxQ&s",
        "productos": [
            {
                "id": 1,
                "nombre": "BUCHANANS 12",
                "precio": 749,
                "cantidad": 1000,
                "fotoUrl": "https://http2.mlstatic.com/D_NQ_NP_739193-MLC47570746590_092021-O.webp",
                "descripcion": "Un whisky escocés blended de 12 años, conocido por su suavidad y cuerpo ligero. Ofrece notas de miel, manzanas verdes y roble, con un final cremoso y dulce. Ideal para ocasiones especiales o para mezclar en cocteles premium.",
                "disponible": true
            }
        ]
    },
    {
        "id": 5,
        "nombre": "Herradura",
        "fotoUrl": "https://cdn.uc.assets.prezly.com/9ac7ff03-8be0-46ed-b446-4b2323d6966a/US%2B-%2BHerradura%2BCore%2BFamily%2Band%2BUltra%2B-%2BKey%2BVisual.jpg",
        "productos": [
            {
                "id": 1,
                "nombre": "HERRADURA ULTRA",
                "precio": 679,
                "cantidad": 1000,
                "fotoUrl": "https://encrypted-tbn0.gstatic.com/images?q=tbn:ANd9GcRzQe05IZeeUiuqOC0ogDDG0n592JUUu75dvw&s",
                "descripcion": "Un tequila añejo cristalino ultra premium, mezcla de añejo y extra añejo con un toque de néctar de agave. Ofrece un perfil suave y dulce, con notas de almendra tostada y vainilla. Perfecto para disfrutar solo en su máxima expresión.",
                "disponible": true
            }
        ]
    },
    {
        "id": 6,
        "nombre": "Dobel",
        "fotoUrl": "https://http2.mlstatic.com/D_NQ_NP_690195-MLB53484387949_012023-O.webp",
        "productos": [
            {
                "id": 1,
                "nombre": "MAESTRO DOBEL",
                "precio": 599,
                "cantidad": 1000,
                "fotoUrl": "https://encrypted-tbn0.gstatic.com/images?q=tbn:ANd9GcQ55G2NZ6n0CIAe56Plry65-V2YEyQVzUSFkA&s",
                "descripcion": "Tequila innovador y sofisticado, elaborado con agave azul y destilado con un proceso artesanal. Ofrece un perfil suave y complejo, con notas de roble, caramelo y un toque de especias. Ideal para disfrutar solo o en cócteles premium.",
                "disponible": true
            }
        ]
    },
    {
        "id": 7,
        "nombre": "1800",
        "fotoUrl": "https://encrypted-tbn0.gstatic.com/images?q=tbn:ANd9GcSkFUaToe8BXmNKLEenIfnCA4sytyly6hlbAg&s",
        "productos": [
            {
                "id": 1,
                "nombre": "1800 CRISTALINO",
                "precio": 599,
                "cantidad": 1000,
                "fotoUrl": "https://encrypted-tbn0.gstatic.com/images?q=tbn:ANd9GcSsBbLHBUGWR6QSUcE16aeBwnC1q3YQYeQYew&s",
                "descripcion": "Un tequila añejo cristalino que combina la suavidad del añejamiento con una pureza visual impecable. Tiene sabores ricos de caramelo y vainilla con un toque de frutos secos, ofreciendo una experiencia elegante y refinada.",
                "disponible": true
            }
        ]
    },
    {
        "id": 8,
        "nombre": "Torres",
        "fotoUrl": "https://encrypted-tbn0.gstatic.com/images?q=tbn:ANd9GcSye5J1WbR126O8TxdYbs9XCeXNbC6MSsnDTk9qm5LTNPG_2exZRUVNHeoT20Y-mIt8cPI&usqp=CAU",
        "productos": [
            {
                "id": 1,
                "nombre": "TORRES 10",
                "precio": 350,
                "cantidad": 1000,
                "fotoUrl": "https://encrypted-tbn0.gstatic.com/images?q=tbn:ANd9GcSem4m9_k90i0gakb0mhdn59zkN5iJm_w4JaQ&s",
                "descripcion": "Un brandy español de calidad superior, envejecido en barricas de roble americano. Su perfil es intenso y equilibrado, con sabores de vainilla, canela y nueces tostadas. Perfecto para disfrutar solo o con hielo.",
                "disponible": true
            }
        ]
    }
]